pyven/Dockerfile.aridt
pyven/README.md.aridt
pyven/__init__.py
pyven/bdist.py
pyven/checks.py
pyven/container.py
pyven/execcheck.py
pyven/files.py
pyven/functions.py
pyven/licheck.py
pyven/mainmodules.py
pyven/metacheck.py
pyven/minreqs.py
pyven/nlcheck.py
pyven/patchpolicy.py
pyven/pipify.py
pyven/projectinfo.arid
pyven/projectinfo.py
pyven/pyproject.toml.aridt
pyven/release.arid
pyven/release.py
pyven/setup.py.aridt
pyven/setuptools.arid
pyven/sourceinfo.py
pyven/tasks.py
pyven/tryinstall.py
pyven/util.py
pyven/tests/__init__.py
pyven-116.dist-info/METADATA
pyven-116.dist-info/WHEEL
pyven-116.dist-info/entry_points.txt
pyven-116.dist-info/top_level.txt
pyven-116.dist-info/RECORD
