Metadata-Version: 2.1
Name: pyven
Version: 116
Summary: Manage development of multiple Python projects
Home-page: https://pypi.org/project/pyven/
Author: Homsar
Author-email: homsar@foyono.com
Requires-Dist: aridity >=85
Requires-Dist: diapyr >=31
Requires-Dist: foyndation >=10
Requires-Dist: lagoon >=49
Requires-Dist: pydoc-markdown >=3.3
Requires-Dist: roman >=5
Requires-Dist: setuptools >=44.1.1
Requires-Dist: twine >=1.15.0
Requires-Dist: venvpool >=18
